radiosim/__init__.py
radiosim/_version.py
radiosim/flux_scaling.py
radiosim/gauss.py
radiosim/jet.py
radiosim/mojave.py
radiosim/ppdisks.py
radiosim/simulations.py
radiosim/survey.py
radiosim/utils.py
radiosim/version.py
radiosim/scripts/simulate_ppdisks.py
radiosim/scripts/start_simulation.py
radiosim-0.1.1.dist-info/METADATA
radiosim-0.1.1.dist-info/WHEEL
radiosim-0.1.1.dist-info/entry_points.txt
radiosim-0.1.1.dist-info/licenses/LICENSE
radiosim-0.1.1.dist-info/RECORD
