Metadata-Version: 2.4
Name: radiosim
Version: 0.1.1
Summary: Simulation of radio skies to create astrophysical data sets
Project-URL: Repository, https://github.com/radionets-project/radiosim
Author: radionets Developers
Maintainer-email: Kevin Schmitz <kevin2.schmiz@tu-dortmund.de>, Christian Arauner <christian.arauner@tu-dortmund.de>
License: MIT
License-File: LICENSE
Classifier: Development Status :: 3 - Alpha
Classifier: Intended Audience :: Science/Research
Classifier: License :: OSI Approved :: MIT License
Classifier: Natural Language :: English
Classifier: Operating System :: OS Independent
Classifier: Programming Language :: Python
Classifier: Programming Language :: Python :: 3 :: Only
Classifier: Programming Language :: Python :: 3.9
Classifier: Topic :: Scientific/Engineering :: Astronomy
Classifier: Topic :: Scientific/Engineering :: Physics
Requires-Python: >=3.11
Requires-Dist: astropy
Requires-Dist: click
Requires-Dist: h5py
Requires-Dist: joblib
Requires-Dist: numpy
Requires-Dist: opencv-python
Requires-Dist: pathlib
Requires-Dist: rich
Requires-Dist: scikit-image
Requires-Dist: scipy
Requires-Dist: toml
Requires-Dist: tqdm
Provides-Extra: torch
Requires-Dist: torch; extra == 'torch'
Requires-Dist: torchvision; extra == 'torch'
